odoo/addons/purchase_receipt_expectation/README.rst
odoo/addons/purchase_receipt_expectation/__init__.py
odoo/addons/purchase_receipt_expectation/__manifest__.py
odoo/addons/purchase_receipt_expectation/i18n/fr.po
odoo/addons/purchase_receipt_expectation/i18n/it.po
odoo/addons/purchase_receipt_expectation/i18n/pt_BR.po
odoo/addons/purchase_receipt_expectation/i18n/purchase_receipt_expectation.pot
odoo/addons/purchase_receipt_expectation/models/__init__.py
odoo/addons/purchase_receipt_expectation/models/purchase_order.py
odoo/addons/purchase_receipt_expectation/readme/CONTRIBUTORS.md
odoo/addons/purchase_receipt_expectation/readme/DESCRIPTION.md
odoo/addons/purchase_receipt_expectation/readme/USAGE.md
odoo/addons/purchase_receipt_expectation/static/description/icon.png
odoo/addons/purchase_receipt_expectation/static/description/index.html
odoo/addons/purchase_receipt_expectation/tests/__init__.py
odoo/addons/purchase_receipt_expectation/tests/test_purchase_receipt_expectation.py
odoo/addons/purchase_receipt_expectation/views/purchase_order.xml
odoo_addon_purchase_receipt_expectation-18.0.1.0.0.5.dist-info/METADATA
odoo_addon_purchase_receipt_expectation-18.0.1.0.0.5.dist-info/WHEEL
odoo_addon_purchase_receipt_expectation-18.0.1.0.0.5.dist-info/top_level.txt
odoo_addon_purchase_receipt_expectation-18.0.1.0.0.5.dist-info/RECORD
